robotvibecoder/__init__.py
robotvibecoder/cli.py
robotvibecoder/config.py
robotvibecoder/constants.py
robotvibecoder/main.py
robotvibecoder/templating.py
robotvibecoder/subcommands/generate.py
robotvibecoder/subcommands/new.py
robotvibecoder/templates/ArmSim.java.j2
robotvibecoder/templates/ElevatorSim.java.j2
robotvibecoder/templates/Mechanism.java.j2
robotvibecoder/templates/MechanismConstants.java.j2
robotvibecoder/templates/MechanismIO.java.j2
robotvibecoder/templates/MechanismIOSim.java.j2
robotvibecoder/templates/MechanismIOTalonFX.java.j2
robotvibecoder-0.0.5.dist-info/METADATA
robotvibecoder-0.0.5.dist-info/WHEEL
robotvibecoder-0.0.5.dist-info/entry_points.txt
robotvibecoder-0.0.5.dist-info/licenses/LICENSE
robotvibecoder-0.0.5.dist-info/RECORD
