Metadata-Version: 2.4
Name: robotvibecoder
Version: 0.0.5
Project-URL: Documentation, https://github.com/team401/robotvibecoder#readme
Project-URL: Issues, https://github.com/team401/robotvibecoder/issues
Project-URL: Source, https://github.com/team401/robotvibecoder
Author: team401
License-Expression: GPL-3.0
License-File: LICENSE
Classifier: Development Status :: 4 - Beta
Classifier: Programming Language :: Python
Classifier: Programming Language :: Python :: 3.8
Classifier: Programming Language :: Python :: 3.9
Classifier: Programming Language :: Python :: 3.10
Classifier: Programming Language :: Python :: 3.11
Classifier: Programming Language :: Python :: 3.12
Classifier: Programming Language :: Python :: Implementation :: CPython
Classifier: Programming Language :: Python :: Implementation :: PyPy
Requires-Python: >=3.8
Requires-Dist: jinja2==3.1.6
Requires-Dist: pick==2.4.0
Requires-Dist: prompt-toolkit==3.0.51
